gengine/__about__.py
gengine/__init__.py
gengine/generator_engine.py
gengine-0.1.0.dist-info/METADATA
gengine-0.1.0.dist-info/WHEEL
gengine-0.1.0.dist-info/licenses/LICENSE.txt
gengine-0.1.0.dist-info/RECORD
