Metadata-Version: 2.3
Name: gengine
Version: 0.1.0
Summary: Engine for piping generators
Project-URL: Documentation, https://github.com/m-birke/gengine#readme
Project-URL: Issues, https://github.com/m-birke/gengine/issues
Project-URL: Source, https://github.com/m-birke/gengine
Author-email: m-birke <wesci@web.de>
License-Expression: MIT
License-File: LICENSE.txt
Keywords: data,engine,generator,pipeline,stream,workflow
Classifier: Development Status :: 4 - Beta
Classifier: Programming Language :: Python
Classifier: Programming Language :: Python :: 3.8
Classifier: Programming Language :: Python :: 3.9
Classifier: Programming Language :: Python :: 3.10
Classifier: Programming Language :: Python :: 3.11
Classifier: Programming Language :: Python :: 3.12
Classifier: Programming Language :: Python :: Implementation :: CPython
Classifier: Programming Language :: Python :: Implementation :: PyPy
Requires-Python: >=3.8
